drifter_ml/__init__.py
drifter_ml/classification_tests/__init__.py
drifter_ml/classification_tests/classification_tests.py
drifter_ml/columnar_tests/__init__.py
drifter_ml/columnar_tests/columnar_tests.py
drifter_ml/regression_tests/__init__.py
drifter_ml/regression_tests/regression_tests.py
drifter_ml/structural_tests/__init__.py
drifter_ml/structural_tests/structural_tests.py
drifter_ml-0.26.dist-info/licenses/LICENSE
drifter_ml-0.26.dist-info/METADATA
drifter_ml-0.26.dist-info/WHEEL
drifter_ml-0.26.dist-info/top_level.txt
drifter_ml-0.26.dist-info/RECORD
