Metadata-Version: 2.4
Name: drifter_ml
Version: 0.26
Summary: Testing for models confirming to the scikit-learn api
Home-page: https://github.com/EricSchles/drifter_ml
Author: Eric Schles
Author-email: ericschles@gmail.com
License: MIT
Classifier: License :: OSI Approved :: MIT License
Classifier: Programming Language :: Python :: 3
License-File: LICENSE
Requires-Dist: scikit-learn
Requires-Dist: scipy
Requires-Dist: numpy
Requires-Dist: statsmodels
Requires-Dist: mlxtend
Requires-Dist: pytest
Requires-Dist: energyusage
Requires-Dist: backtester
Dynamic: author
Dynamic: author-email
Dynamic: classifier
Dynamic: description
Dynamic: description-content-type
Dynamic: home-page
Dynamic: license
Dynamic: license-file
Dynamic: requires-dist
Dynamic: summary
